pmicli
