Metadata-Version: 2.1
Name: pmicli
Version: 0.0.5
Summary: pmicli helper scripts
Author: walid.boussafa@dotmatics.com
Classifier: Programming Language :: Python :: 3.7
Classifier: Programming Language :: Python :: 3.8
Classifier: Programming Language :: Python :: 3.9
Classifier: Programming Language :: Python :: 3.10
Classifier: Programming Language :: Python :: 3.11
Classifier: Programming Language :: Python :: 3.12
Classifier: Operating System :: OS Independent
Classifier: Development Status :: 1 - Planning 
Requires-Dist: typer
Requires-Dist: rich
Requires-Dist: shellingham
Requires-Dist: conan<2,>=1.64.0
Requires-Dist: pmi-conan-package-tools
